fastdbfs/__init__.py
fastdbfs/cli.py
fastdbfs/cmdline.py
fastdbfs/dbfs.py
fastdbfs/exceptions.py
fastdbfs/fileinfo.py
fastdbfs/format.py
fastdbfs/runner.py
fastdbfs/swarm.py
fastdbfs/util.py
fastdbfs-0.5.dist-info/LICENSE.txt
fastdbfs-0.5.dist-info/METADATA
fastdbfs-0.5.dist-info/WHEEL
fastdbfs-0.5.dist-info/entry_points.txt
fastdbfs-0.5.dist-info/top_level.txt
fastdbfs-0.5.dist-info/RECORD
