Metadata-Version: 2.1
Name: fastdbfs
Version: 0.5
Summary: Interactive command line client for Databricks DBFS
Home-page: http://github.com/salva/fastdbfs
Author: Salvador Fandiño García
Author-email: sfandino@yahoo.com
License: GPLv3
Platform: UNKNOWN
Requires-Dist: aiohttp
Requires-Dist: dateparser
Requires-Dist: humanfriendly
Requires-Dist: progressbar2
